dtBotSDK/__init__.py
dtBotSDK/dingTalkBotSDK.py
dtBotSDK-1.0.dist-info/METADATA
dtBotSDK-1.0.dist-info/WHEEL
dtBotSDK-1.0.dist-info/top_level.txt
dtBotSDK-1.0.dist-info/RECORD
