Metadata-Version: 2.1
Name: dtBotSDK
Version: 1.0
Summary: UNKNOWN
Home-page: UNKNOWN
Author: arthurtung
License: LGPL
Platform: UNKNOWN
Requires-Dist: requests
